{
  "collectionName": "components_caterers_restorans",
  "info": {
    "displayName": "restoran",
    "description": ""
  },
  "options": {},
  "attributes": {
    "radnoVrijeme": {
      "type": "time"
    },
    "ime": {
      "type": "string"
    },
    "fotoMain": {
      "type": "media",
      "multiple": false,
      "required": false,
      "allowedTypes": [
        "images",
        "files",
        "videos",
        "audios"
      ]
    },
    "users": {
      "type": "relation",
      "relation": "oneToMany",
      "target": "admin::user"
    }
  }
}
